examples/example.py
src/taxes/FlatTax.py
src/taxes/FlatTaxBracket.py
src/taxes/Logger.py
src/taxes/ProgressiveTax.py
src/taxes/ProgressiveTaxBracket.py
src/taxes/RegressiveTax.py
src/taxes/RegressiveTaxBracket.py
src/taxes/__init__.py
src/taxes/brackets/FederalIncomeTaxBrackets.py
src/taxes/brackets/GeorgiaStateIncomeTaxBrackets.py
src/taxes/brackets/MedicareIncomeTaxBrackets.py
src/taxes/brackets/SocialSecurityIncomeTaxBrackets.py
src/taxes/brackets/__init__.py
personal_taxes-0.0.2.dist-info/METADATA
personal_taxes-0.0.2.dist-info/WHEEL
personal_taxes-0.0.2.dist-info/licenses/LICENSE
personal_taxes-0.0.2.dist-info/RECORD
