Metadata-Version: 2.1
Name: personal_taxes
Version: 0.0.2
Summary: A lightweight package for personal income taxes
Project-URL: Homepage, https://github.com/leehagoodjames/taxes
Project-URL: Bug Tracker, https://github.com/leehagoodjames/taxes/issues
Author-email: Lee James <leehagoodjames@gmail.com>
License-File: LICENSE
Classifier: License :: OSI Approved :: MIT License
Classifier: Operating System :: OS Independent
Classifier: Programming Language :: Python :: 3
Requires-Python: >=3.3
